{
  "itensColetasDados": [
    {
      "label": "XLXS",
      "movido": false,
      "tipoItem": "coleta-dado",
      "habilitado": true
    },
    {
      "label": "CSV",
      "movido": false,
      "tipoItem": "coleta-dado",
      "habilitado": true
    },
    {
      "label": "JSON",
      "movido": false,
      "tipoItem": "coleta-dado",
      "habilitado": true
    }
  ],
  "itensTreino": [
    {
      "label": "k-NN",
      "movido": false,
      "tipoItem": "treino-validacao-teste",
      "habilitado": false,
      "valor": "knn",
      "resumo": "k-NN é um classificador baseado em instâncias que classifica um dado novo com base na maioria dos k vizinhos mais próximos.",
      "tipo": "string",
      "hiperparametros": [
        {
          "label": "Número de vizinhos",
          "nomeHiperparametro": "n_neighbors",
          "valorPadrao": 5,
          "tipo": "int"
        }
      ],
      "metricas": [
        "precision_score",
        "recall_score",
        "f1_score",
        "confusion_matrix"
      ]
    },
    {
      "label": "Árvore de Decisão",
      "movido": false,
      "tipoItem": "treino-validacao-teste",
      "habilitado": false,
      "valor": "arvore_decisao",
      "resumo": "Árvore de Decisão cria um modelo em forma de árvore para tomar decisões baseadas em características dos dados.",
      "tipo": "string",
      "hiperparametros": [],
      "metricas": [
        "accuracy_score",
        "precision_score",
        "recall_score",
        "f1_score",
        "confusion_matrix"
      ]
    },
    {
      "label": "SVM",
      "movido": false,
      "tipoItem": "treino-validacao-teste",
      "habilitado": false,
      "valor": "svm",
      "resumo": "SVM busca um hiperplano que separa as classes com a maior margem possível no espaço de características.",
      "tipo": "string",
      "hiperparametros": [],
      "metricas": [
        "accuracy_score",
        "precision_score",
        "recall_score",
        "f1_score",
        "confusion_matrix"
      ]
    },
    {
      "label": "Regressão Logística",
      "movido": false,
      "tipoItem": "treino-validacao-teste",
      "habilitado": false,
      "valor": "regressao_logistica",
      "resumo": "Regressão Logística modela a probabilidade de uma classe binária usando a função logística.",
      "tipo": "string",
      "hiperparametros": [],
      "metricas": [
        "accuracy_score",
        "precision_score",
        "recall_score",
        "f1_score",
        "confusion_matrix"
      ]
    },
    {
      "label": "Regressão Linear",
      "movido": false,
      "tipoItem": "treino-validacao-teste",
      "habilitado": false,
      "valor": "regressao_linear",
      "resumo": "Regressão Linear ajusta uma reta que minimiza o erro quadrático médio entre as previsões e os valores reais.",
      "tipo": "number",
      "hiperparametros": []
    }
  ],
  "itensMetricas": [
    {
      "label": "Acurácia",
      "resumo": "Proporção de acertos",
      "valor": "accuracy_score",
      "movido": false,
      "tipoItem": "metrica",
      "habilitado": false
    },
    {
      "label": "Precisão",
      "resumo": "Positivos corretos / Total de positivos previstos",
      "valor": "precision_score",
      "movido": false,
      "tipoItem": "metrica",
      "habilitado": false
    },
    {
      "label": "Recall",
      "resumo": "Positivos corretos / Total de positivos reais",
      "valor": "recall_score",
      "movido": false,
      "tipoItem": "metrica",
      "habilitado": false
    },
    {
      "label": "F1-Score",
      "resumo": "Razão entre Precisão e Recall",
      "valor": "f1_score",
      "movido": false,
      "tipoItem": "metrica",
      "habilitado": false
    },
    {
      "label": "Matriz de Confusão",
      "resumo": "Quantidade de acertos e erros por classe",
      "valor": "confusion_matrix",
      "movido": false,
      "tipoItem": "metrica",
      "habilitado": false
    }
  ]
}